{
	"configurations" : 
	[
		{
			"directories" : 
			[
				{
					"build" : ".",
					"hasInstallRule" : true,
					"jsonFile" : "directory-.-Debug-05b8a9a1f38090a6d839.json",
					"minimumCMakeVersion" : 
					{
						"string" : "3.16"
					},
					"projectIndex" : 0,
					"source" : ".",
					"targetIndexes" : 
					[
						0,
						1,
						2
					]
				}
			],
			"name" : "Debug",
			"projects" : 
			[
				{
					"directoryIndexes" : 
					[
						0
					],
					"name" : "Painting",
					"targetIndexes" : 
					[
						0,
						1,
						2
					]
				}
			],
			"targets" : 
			[
				{
					"directoryIndex" : 0,
					"id" : "Painting::@6890427a1f51a3e7e1df",
					"jsonFile" : "target-Painting-Debug-bd892c18cb586a37469f.json",
					"name" : "Painting",
					"projectIndex" : 0
				},
				{
					"directoryIndex" : 0,
					"id" : "Painting_autogen::@6890427a1f51a3e7e1df",
					"jsonFile" : "target-Painting_autogen-Debug-39f92aad5a3a88a9d4a4.json",
					"name" : "Painting_autogen",
					"projectIndex" : 0
				},
				{
					"directoryIndex" : 0,
					"id" : "Painting_autogen_timestamp_deps::@6890427a1f51a3e7e1df",
					"jsonFile" : "target-Painting_autogen_timestamp_deps-Debug-96537a30f6b7e557fb35.json",
					"name" : "Painting_autogen_timestamp_deps",
					"projectIndex" : 0
				}
			]
		}
	],
	"kind" : "codemodel",
	"paths" : 
	{
		"build" : "D:/Projects/QtUI/build-Painting-Desktop_Qt_shared_MinGW_w64_MINGW64_MSYS2-Debug",
		"source" : "D:/Projects/QtUI/Painting"
	},
	"version" : 
	{
		"major" : 2,
		"minor" : 5
	}
}
